odoo/addons/project_wbs/README.rst
odoo/addons/project_wbs/__init__.py
odoo/addons/project_wbs/__manifest__.py
odoo/addons/project_wbs/hooks.py
odoo/addons/project_wbs/i18n/es.po
odoo/addons/project_wbs/i18n/project_wbs.pot
odoo/addons/project_wbs/models/__init__.py
odoo/addons/project_wbs/models/account_analytic_account.py
odoo/addons/project_wbs/models/project_project.py
odoo/addons/project_wbs/static/description/icon.png
odoo/addons/project_wbs/tests/__init__.py
odoo/addons/project_wbs/tests/test_project_wbs.py
odoo/addons/project_wbs/view/account_analytic_account_view.xml
odoo/addons/project_wbs/view/project_project_view.xml
odoo11_addon_project_wbs-11.0.1.0.0.99.dev4.dist-info/METADATA
odoo11_addon_project_wbs-11.0.1.0.0.99.dev4.dist-info/WHEEL
odoo11_addon_project_wbs-11.0.1.0.0.99.dev4.dist-info/top_level.txt
odoo11_addon_project_wbs-11.0.1.0.0.99.dev4.dist-info/RECORD
